Metadata-Version: 2.1
Name: pokepi
Version: 0.0-0
Summary: Pokemon API
Home-page: UNKNOWN
Author: VarMonke
License: MIT
Platform: UNKNOWN
License-File: LICENSE
